tcp_rsync/__init__.py
tcp_rsync/main.py
tcp_rsync/metadata.py
tcp_rsync-0.1rc0.dist-info/DESCRIPTION.rst
tcp_rsync-0.1rc0.dist-info/METADATA
tcp_rsync-0.1rc0.dist-info/RECORD
tcp_rsync-0.1rc0.dist-info/WHEEL
tcp_rsync-0.1rc0.dist-info/entry_points.txt
tcp_rsync-0.1rc0.dist-info/metadata.json
tcp_rsync-0.1rc0.dist-info/top_level.txt
