Metadata-Version: 2.0
Name: tcp-rsync
Version: 0.1rc0
Summary: 1. Quick Deployment Of Rsync Daemon For TCP Transmission; 2. Encapsulation For Commonly Used Operations. 
Home-page: UNKNOWN
Author: huntzhan
Author-email: programmer.zhx@gmail.com
License: UNKNOWN
Platform: UNKNOWN
Classifier: License :: OSI Approved :: MIT License
Classifier: Development Status :: 1 - Planning
Classifier: Intended Audience :: Developers
Classifier: Topic :: Software Development :: Libraries
Classifier: Programming Language :: Python :: 2.7
Classifier: Programming Language :: Python :: 3.3
Classifier: Programming Language :: Python :: 3.4
Classifier: Programming Language :: Python :: 3.5
Requires-Dist: coveralls
Requires-Dist: future
Requires-Dist: pytest (>=2.7.2)
Requires-Dist: pytest-cov
Requires-Dist: pytest-flake8
Requires-Dist: pytest-mock
Requires-Dist: pytest-travis-fold
Requires-Dist: setuptools-scm
Requires-Dist: wheel
